air_markdown/__init__.py
air_markdown/tags.py
air_markdown-0.5.0.dist-info/licenses/LICENSE
air_markdown-0.5.0.dist-info/METADATA
air_markdown-0.5.0.dist-info/WHEEL
air_markdown-0.5.0.dist-info/top_level.txt
air_markdown-0.5.0.dist-info/RECORD
