Metadata-Version: 2.4
Name: air-markdown
Version: 0.5.0
Summary: Air Tags + Markdown
Author-email: Daniel Roy Greenfeld <daniel@feldroy.com>, Audrey Roy Greenfeld <audrey@feldroy.com>
Maintainer-email: Daniel Roy Greenfeld <daniel@feldroy.com>, Audrey Roy Greenfeld <audrey@feldroy.com>
License: MIT
Project-URL: bugs, https://github.com/feldroy/air_markdown/issues
Project-URL: changelog, https://github.com/feldroy/air_markdown/blob/master/changelog.md
Project-URL: homepage, https://github.com/feldroy/air_markdown
Classifier: Operating System :: OS Independent
Classifier: Programming Language :: Python :: 3
Classifier: Programming Language :: Python
Classifier: Topic :: Internet
Classifier: Topic :: Software Development :: Libraries :: Application Frameworks
Classifier: Topic :: Software Development :: Libraries :: Python Modules
Classifier: Topic :: Software Development :: Libraries
Classifier: Topic :: Software Development
Classifier: Typing :: Typed
Classifier: Development Status :: 3 - Alpha
Classifier: Environment :: Web Environment
Classifier: Framework :: FastAPI
Classifier: Intended Audience :: Developers
Classifier: Programming Language :: Python :: 3 :: Only
Classifier: Programming Language :: Python :: 3.13
Requires-Python: >=3.13
License-File: LICENSE
Requires-Dist: air>=0.45.0
Requires-Dist: mistletoe>=1.4.0
Provides-Extra: dev
Requires-Dist: rust-just; extra == "dev"
Provides-Extra: test
Requires-Dist: coverage; extra == "test"
Requires-Dist: pytest; extra == "test"
Requires-Dist: ruff; extra == "test"
Requires-Dist: ty; extra == "test"
Requires-Dist: ipdb; extra == "test"
Dynamic: license-file
